{
  "classname": null,
  "name": null,
  "animation": {
    "classname": null,
    "name": "AnimationManager",
    "actionlist": []
  },
  "dataScale": 1,
  "designHeight": 960,
  "designWidth": 640,
  "textures": [
    "gameLayer/game-daoju.plist",
    "gamemenu/game_menu.plist",
    "shop/shopUi.plist",
    "shop.plist"
  ],
  "texturesPng": [
    "gameLayer/game-daoju.plist",
    "gamemenu/game_menu.plist",
    "gameLayer/shangfangui.png",
    "zanting/zantingbg.png",
    "gamemenu/game_menu.plist",
    "gameover/shengli_bg.png",
    "gamemenu/game_menu.plist",
    "gameover/shengli_hua.png",
    "gameover/shengli_xiao.png",
    "gameover/guang.png",
    "gameover/shibai_bg.png",
    "gamemenu/game_menu.plist",
    "gameover/gameover.png",
    "gameover/shibai_ku.png",
    "mainLayer/fengmian.png",
    "touming.png",
    "mainLayer/MainPlay.png",
    "mainLayer/MoreGame.png",
    "gamemenu/game_menu.plist",
    "gamemenu/game_menu.plist",
    "gameLayer/game-daoju.plist",
    "shop/shopUi.plist",
    "shop/mianban.png",
    "zhujue/chengzi.png",
    "zhujue/xigua.png",
    "zhujue/shiliu.png",
    "xuanguan/xuanguan_bg.png",
    "xuanguan/xuanguan_bt_off.png",
    "xuanguan/xiaoxing_off.png",
    "gamemenu/game_menu.plist",
    "shop/mianban.png",
    "GUI/image.png",
    "GUI/button.png",
    "shop-daojuTiao.png",
    "shop.plist",
    "GUI/button.png",
    "GUI/image.png",
    "shop-daojuTiao.png",
    "GUI/image.png",
    "GUI/button.png",
    "tujian/tujianNewBg.png",
    "touming.png",
    "gamemenu/game_menu.plist",
    "tujian/tujianguang.png",
    "jieshao/jieshao_bg.png",
    "gamemenu/game_menu.plist",
    "zhujue/xigua.png",
    "zhujue/chengzi.png",
    "zhujue/shiliu.png",
    "gameover/shibai_bg.png",
    "gamemenu/game_menu.plist",
    "shibaiwenzi.jpg",
    "gameover/gameover.png",
    "gameover/shibai_ku.png",
    "selectLevel.png",
    "a.png",
    "GUI/button.png",
    "gameLayer/game-daoju.plist",
    "shop/shopUi.plist",
    "zanting/zantingbg.png",
    "gamemenu/game_menu.plist",
    "tujian/tujianbg.png",
    "touming.png",
    "gamemenu/game_menu.plist",
    "tujian/tujianguang.png",
    "tujian/bantouming.png",
    "gameLayer/game-daoju.plist",
    "gameLayer/shangfangui.png",
    "gamemenu/game_menu.plist",
    "gameLayer/game-daoju.plist",
    "gameLayer/xuetiao_di.png",
    "gameLayer/xuetiao.png",
    "tujian/kapian.png",
    "touming.png",
    "gamemenu/game_menu.plist",
    "mainLayer/fengmian.png",
    "touming.png",
    "mainLayer/MainPlay.png",
    "mainLayer/wenzi_play.png",
    "mainLayer/wenzi_moregame.png",
    "gamemenu/game_menu.plist"
  ],
  "version": "1.6.0.0",
  "widgetTree": {
    "classname": "Panel",
    "name": null,
    "children": [
      {
        "classname": "ImageView",
        "name": null,
        "children": [],
        "options": {
          "__type": "ImageViewSurrogate:#EditorCommon.JsonModel.Component.GUI",
          "classname": "ImageView",
          "name": "Image_1",
          "ZOrder": 0,
          "actiontag": 43797605,
          "anchorPointX": 0.5,
          "anchorPointY": 0.5,
          "classType": "CocoStudio.EngineAdapterWrap.CSImageView",
          "colorB": 255,
          "colorG": 255,
          "colorR": 255,
          "customProperty": "",
          "flipX": false,
          "flipY": false,
          "height": 960,
          "ignoreSize": true,
          "layoutParameter": null,
          "opacity": 255,
          "positionPercentX": 0.5046875,
          "positionPercentY": 0.495833337,
          "positionType": 0,
          "rotation": 0,
          "scaleX": 1,
          "scaleY": 1,
          "sizePercentX": 1,
          "sizePercentY": 1,
          "sizeType": 0,
          "tag": 117,
          "touchAble": false,
          "useMergedTexture": false,
          "visible": true,
          "width": 640,
          "x": 323,
          "y": 476,
          "capInsetsHeight": 1,
          "capInsetsWidth": 1,
          "capInsetsX": 0,
          "capInsetsY": 0,
          "fileName": null,
          "fileNameData": {
            "path": "mainLayer/fengmian.png",
            "plistFile": "",
            "resourceType": 0
          },
          "scale9Enable": false,
          "scale9Height": 960,
          "scale9Width": 640
        }
      },
      {
        "classname": "Button",
        "name": null,
        "children": [],
        "options": {
          "__type": "ButtonSurrogate:#EditorCommon.JsonModel.Component.GUI",
          "classname": "Button",
          "name": "onPlay2",
          "ZOrder": 0,
          "actiontag": 29346720,
          "anchorPointX": 0.5,
          "anchorPointY": 0.5,
          "classType": "CocoStudio.EngineAdapterWrap.CSButton",
          "colorB": 255,
          "colorG": 255,
          "colorR": 255,
          "customProperty": "",
          "flipX": false,
          "flipY": false,
          "height": 20,
          "ignoreSize": true,
          "layoutParameter": null,
          "opacity": 255,
          "positionPercentX": 0.5,
          "positionPercentY": 0.492708325,
          "positionType": 0,
          "rotation": 0,
          "scaleX": 31.244009,
          "scaleY": 36.40508,
          "sizePercentX": 0.03125,
          "sizePercentY": 0.020833334,
          "sizeType": 0,
          "tag": 121,
          "touchAble": true,
          "useMergedTexture": false,
          "visible": true,
          "width": 20,
          "x": 320,
          "y": 473,
          "capInsetsHeight": 1,
          "capInsetsWidth": 1,
          "capInsetsX": 0,
          "capInsetsY": 0,
          "disabled": null,
          "disabledData": {
            "path": null,
            "plistFile": null,
            "resourceType": 0
          },
          "fontName": "微软雅黑",
          "fontSize": 14,
          "fontType": 0,
          "normal": null,
          "normalData": {
            "path": "touming.png",
            "plistFile": "",
            "resourceType": 0
          },
          "pressed": null,
          "pressedData": {
            "path": null,
            "plistFile": null,
            "resourceType": 0
          },
          "scale9Enable": false,
          "scale9Height": 20,
          "scale9Width": 20,
          "text": "",
          "textColorB": 255,
          "textColorG": 255,
          "textColorR": 255
        }
      },
      {
        "classname": "Button",
        "name": null,
        "children": [
          {
            "classname": "ImageView",
            "name": null,
            "children": [],
            "options": {
              "__type": "ImageViewSurrogate:#EditorCommon.JsonModel.Component.GUI",
              "classname": "ImageView",
              "name": "touming",
              "ZOrder": 0,
              "actiontag": 40655501,
              "anchorPointX": 0.5,
              "anchorPointY": 0.5,
              "classType": "CocoStudio.EngineAdapterWrap.CSImageView",
              "colorB": 255,
              "colorG": 255,
              "colorR": 255,
              "customProperty": "",
              "flipX": false,
              "flipY": false,
              "height": 20,
              "ignoreSize": true,
              "layoutParameter": null,
              "opacity": 255,
              "positionPercentX": 0,
              "positionPercentY": 0.08264463,
              "positionType": 0,
              "rotation": 0,
              "scaleX": 1,
              "scaleY": 1,
              "sizePercentX": 0.0896860957,
              "sizePercentY": 0.165289253,
              "sizeType": 0,
              "tag": 5753,
              "touchAble": false,
              "useMergedTexture": false,
              "visible": true,
              "width": 20,
              "x": 0,
              "y": 10,
              "capInsetsHeight": 1,
              "capInsetsWidth": 1,
              "capInsetsX": 0,
              "capInsetsY": 0,
              "fileName": null,
              "fileNameData": {
                "path": "touming.png",
                "plistFile": "",
                "resourceType": 0
              },
              "scale9Enable": false,
              "scale9Height": 20,
              "scale9Width": 20
            }
          }
        ],
        "options": {
          "__type": "ButtonSurrogate:#EditorCommon.JsonModel.Component.GUI",
          "classname": "Button",
          "name": "onPlay",
          "ZOrder": 10,
          "actiontag": 28349038,
          "anchorPointX": 0.5,
          "anchorPointY": 0.5,
          "classType": "CocoStudio.EngineAdapterWrap.CSButton",
          "colorB": 255,
          "colorG": 255,
          "colorR": 255,
          "customProperty": "",
          "flipX": false,
          "flipY": false,
          "height": 121,
          "ignoreSize": true,
          "layoutParameter": null,
          "opacity": 255,
          "positionPercentX": 0.8375,
          "positionPercentY": 0.159375,
          "positionType": 0,
          "rotation": 0,
          "scaleX": 1,
          "scaleY": 1,
          "sizePercentX": 0.3484375,
          "sizePercentY": 0.126041666,
          "sizeType": 0,
          "tag": 4456,
          "touchAble": true,
          "useMergedTexture": false,
          "visible": true,
          "width": 223,
          "x": 536,
          "y": 153,
          "capInsetsHeight": 1,
          "capInsetsWidth": 1,
          "capInsetsX": 0,
          "capInsetsY": 0,
          "disabled": null,
          "disabledData": {
            "path": null,
            "plistFile": null,
            "resourceType": 0
          },
          "fontName": "微软雅黑",
          "fontSize": 14,
          "fontType": 0,
          "normal": null,
          "normalData": {
            "path": "mainLayer/MainPlay.png",
            "plistFile": "",
            "resourceType": 0
          },
          "pressed": null,
          "pressedData": {
            "path": null,
            "plistFile": null,
            "resourceType": 0
          },
          "scale9Enable": false,
          "scale9Height": 121,
          "scale9Width": 223,
          "text": "",
          "textColorB": 255,
          "textColorG": 255,
          "textColorR": 255
        }
      },
      {
        "classname": "Button",
        "name": null,
        "children": [
          {
            "classname": "ImageView",
            "name": null,
            "children": [],
            "options": {
              "__type": "ImageViewSurrogate:#EditorCommon.JsonModel.Component.GUI",
              "classname": "ImageView",
              "name": "touming",
              "ZOrder": 0,
              "actiontag": 64861980,
              "anchorPointX": 0.5,
              "anchorPointY": 0.5,
              "classType": "CocoStudio.EngineAdapterWrap.CSImageView",
              "colorB": 255,
              "colorG": 255,
              "colorR": 255,
              "customProperty": "",
              "flipX": false,
              "flipY": false,
              "height": 20,
              "ignoreSize": true,
              "layoutParameter": null,
              "opacity": 255,
              "positionPercentX": 0,
              "positionPercentY": 0.08264463,
              "positionType": 0,
              "rotation": 0,
              "scaleX": 1,
              "scaleY": 1,
              "sizePercentX": 0.06410257,
              "sizePercentY": 0.165289253,
              "sizeType": 0,
              "tag": 5757,
              "touchAble": false,
              "useMergedTexture": false,
              "visible": true,
              "width": 20,
              "x": 0,
              "y": 10,
              "capInsetsHeight": 1,
              "capInsetsWidth": 1,
              "capInsetsX": 0,
              "capInsetsY": 0,
              "fileName": null,
              "fileNameData": {
                "path": "touming.png",
                "plistFile": "",
                "resourceType": 0
              },
              "scale9Enable": false,
              "scale9Height": 20,
              "scale9Width": 20
            }
          }
        ],
        "options": {
          "__type": "ButtonSurrogate:#EditorCommon.JsonModel.Component.GUI",
          "classname": "Button",
          "name": "onMore",
          "ZOrder": 10,
          "actiontag": 45502051,
          "anchorPointX": 0.5,
          "anchorPointY": 0.5,
          "classType": "CocoStudio.EngineAdapterWrap.CSButton",
          "colorB": 255,
          "colorG": 255,
          "colorR": 255,
          "customProperty": "",
          "flipX": false,
          "flipY": false,
          "height": 121,
          "ignoreSize": true,
          "layoutParameter": null,
          "opacity": 255,
          "positionPercentX": 0.7796875,
          "positionPercentY": 0.053125,
          "positionType": 0,
          "rotation": 0,
          "scaleX": 1,
          "scaleY": 1,
          "sizePercentX": 0.4875,
          "sizePercentY": 0.126041666,
          "sizeType": 0,
          "tag": 4460,
          "touchAble": true,
          "useMergedTexture": false,
          "visible": true,
          "width": 312,
          "x": 499,
          "y": 51,
          "capInsetsHeight": 1,
          "capInsetsWidth": 1,
          "capInsetsX": 0,
          "capInsetsY": 0,
          "disabled": null,
          "disabledData": {
            "path": null,
            "plistFile": null,
            "resourceType": 0
          },
          "fontName": "微软雅黑",
          "fontSize": 14,
          "fontType": 0,
          "normal": null,
          "normalData": {
            "path": "mainLayer/MoreGame.png",
            "plistFile": "",
            "resourceType": 0
          },
          "pressed": null,
          "pressedData": {
            "path": null,
            "plistFile": null,
            "resourceType": 0
          },
          "scale9Enable": false,
          "scale9Height": 121,
          "scale9Width": 312,
          "text": "",
          "textColorB": 255,
          "textColorG": 255,
          "textColorR": 255
        }
      },
      {
        "classname": "Button",
        "name": null,
        "children": [],
        "options": {
          "__type": "ButtonSurrogate:#EditorCommon.JsonModel.Component.GUI",
          "classname": "Button",
          "name": "onSound",
          "ZOrder": 0,
          "actiontag": 17102365,
          "anchorPointX": 0.5,
          "anchorPointY": 0.5,
          "classType": "CocoStudio.EngineAdapterWrap.CSButton",
          "colorB": 255,
          "colorG": 255,
          "colorR": 255,
          "customProperty": "",
          "flipX": false,
          "flipY": false,
          "height": 107,
          "ignoreSize": true,
          "layoutParameter": null,
          "opacity": 255,
          "positionPercentX": 0.0859375,
          "positionPercentY": 0.935416639,
          "positionType": 0,
          "rotation": 0,
          "scaleX": 1,
          "scaleY": 1,
          "sizePercentX": 0.175,
          "sizePercentY": 0.111458331,
          "sizeType": 0,
          "tag": 4463,
          "touchAble": true,
          "useMergedTexture": false,
          "visible": true,
          "width": 112,
          "x": 55,
          "y": 898,
          "capInsetsHeight": 1,
          "capInsetsWidth": 1,
          "capInsetsX": 0,
          "capInsetsY": 0,
          "disabled": null,
          "disabledData": {
            "path": null,
            "plistFile": null,
            "resourceType": 0
          },
          "fontName": "微软雅黑",
          "fontSize": 14,
          "fontType": 0,
          "normal": null,
          "normalData": {
            "path": "sound_on.png",
            "plistFile": "gamemenu/game_menu.plist",
            "resourceType": 1
          },
          "pressed": null,
          "pressedData": {
            "path": null,
            "plistFile": null,
            "resourceType": 0
          },
          "scale9Enable": false,
          "scale9Height": 107,
          "scale9Width": 112,
          "text": "",
          "textColorB": 255,
          "textColorG": 255,
          "textColorR": 255
        }
      },
      {
        "classname": "Button",
        "name": null,
        "children": [],
        "options": {
          "__type": "ButtonSurrogate:#EditorCommon.JsonModel.Component.GUI",
          "classname": "Button",
          "name": "onMusic",
          "ZOrder": 0,
          "actiontag": 21070612,
          "anchorPointX": 0.5,
          "anchorPointY": 0.5,
          "classType": "CocoStudio.EngineAdapterWrap.CSButton",
          "colorB": 255,
          "colorG": 255,
          "colorR": 255,
          "customProperty": "",
          "flipX": false,
          "flipY": false,
          "height": 107,
          "ignoreSize": true,
          "layoutParameter": null,
          "opacity": 255,
          "positionPercentX": 0.24375,
          "positionPercentY": 0.934375,
          "positionType": 0,
          "rotation": 0,
          "scaleX": 1,
          "scaleY": 1,
          "sizePercentX": 0.1765625,
          "sizePercentY": 0.111458331,
          "sizeType": 0,
          "tag": 4465,
          "touchAble": true,
          "useMergedTexture": false,
          "visible": true,
          "width": 113,
          "x": 156,
          "y": 897,
          "capInsetsHeight": 1,
          "capInsetsWidth": 1,
          "capInsetsX": 0,
          "capInsetsY": 0,
          "disabled": null,
          "disabledData": {
            "path": null,
            "plistFile": null,
            "resourceType": 0
          },
          "fontName": "微软雅黑",
          "fontSize": 14,
          "fontType": 0,
          "normal": null,
          "normalData": {
            "path": "music_on.png",
            "plistFile": "gamemenu/game_menu.plist",
            "resourceType": 1
          },
          "pressed": null,
          "pressedData": {
            "path": null,
            "plistFile": null,
            "resourceType": 0
          },
          "scale9Enable": false,
          "scale9Height": 107,
          "scale9Width": 113,
          "text": "",
          "textColorB": 255,
          "textColorG": 255,
          "textColorR": 255
        }
      }
    ],
    "options": {
      "__type": "PanelSurrogate:#EditorCommon.JsonModel.Component.GUI",
      "classname": "Panel",
      "name": "Panel_13",
      "ZOrder": 0,
      "actiontag": -1,
      "anchorPointX": 0,
      "anchorPointY": 0,
      "classType": "CocoStudio.EngineAdapterWrap.CSPanel",
      "colorB": 255,
      "colorG": 255,
      "colorR": 255,
      "customProperty": "",
      "flipX": false,
      "flipY": false,
      "height": 960,
      "ignoreSize": false,
      "layoutParameter": null,
      "opacity": 255,
      "positionPercentX": 0,
      "positionPercentY": 0,
      "positionType": 0,
      "rotation": 0,
      "scaleX": 1,
      "scaleY": 1,
      "sizePercentX": 1,
      "sizePercentY": 1,
      "sizeType": 0,
      "tag": 116,
      "touchAble": false,
      "useMergedTexture": false,
      "visible": true,
      "width": 640,
      "x": 0,
      "y": 0,
      "adaptScreen": false,
      "backGroundImage": null,
      "backGroundImageData": null,
      "backGroundScale9Enable": false,
      "bgColorB": 255,
      "bgColorG": 200,
      "bgColorOpacity": 0,
      "bgColorR": 150,
      "bgEndColorB": 255,
      "bgEndColorG": 200,
      "bgEndColorR": 150,
      "bgStartColorB": 255,
      "bgStartColorG": 255,
      "bgStartColorR": 255,
      "capInsetsHeight": 1,
      "capInsetsWidth": 1,
      "capInsetsX": 0,
      "capInsetsY": 0,
      "clipAble": false,
      "colorType": 1,
      "layoutType": 0,
      "vectorX": 0,
      "vectorY": -0.5
    }
  }
}